{
  "_fv": 24,
  "_type": "tool",
  "definition": {
    "renderType": 0,
    "texture": "magical_axe",
    "customModelName": "Normal",
    "name": "Magical Axe",
    "specialInfo": [],
    "creativeTab": {
      "value": "CUSTOM:DCMTools"
    },
    "toolType": "Axe",
    "harvestLevel": 10,
    "efficiency": 15.0,
    "attackSpeed": 1.0,
    "enchantability": 67,
    "damageVsEntity": 10.0,
    "usageCount": 2247,
    "blocksAffected": [],
    "hasGlow": false,
    "repairItems": [
      {
        "value": "CUSTOM:Magical"
      }
    ],
    "immuneToFire": false,
    "stayInGridWhenCrafting": false,
    "damageOnCrafting": false
  }
}